openalex_analysis/__init__.py
openalex_analysis/analysis/__init__.py
openalex_analysis/analysis/entities_analysis.py
openalex_analysis/data/__init__.py
openalex_analysis/data/entities_data.py
openalex_analysis/plot/__init__.py
openalex_analysis/plot/entities_plot.py
openalex_analysis-0.15.dist-info/licenses/LICENCE.txt
openalex_analysis-0.15.dist-info/METADATA
openalex_analysis-0.15.dist-info/WHEEL
openalex_analysis-0.15.dist-info/top_level.txt
openalex_analysis-0.15.dist-info/RECORD
