Metadata-Version: 2.4
Name: openalex-analysis
Version: 0.15
Summary: A python library to download, analyse or plot articles, institutions, and other entities from the OpenAlex API
Author-email: Romain Thomas <contact@romainthomas.net>
License-Expression: GPL-3.0-only
Project-URL: Homepage, https://pypi.org/project/openalex-analysis/
Project-URL: Repository, https://github.com/romain894/openalex-analysis
Project-URL: Documentation, https://romain894.github.io/openalex-analysis/html/index.html
Keywords: OpenAlex,Data analysis,Scientific research,Plotly
Classifier: Development Status :: 3 - Alpha
Classifier: Programming Language :: Python
Classifier: Programming Language :: Python :: 3
Classifier: Intended Audience :: Science/Research
Requires-Python: >=3.10
License-File: LICENCE.txt
Requires-Dist: numpy>=1.21.5
Requires-Dist: pandas>=2.0.1
Requires-Dist: plotly>=5.15.0
Requires-Dist: kaleido<1.0
Requires-Dist: psutil>=5.9.4
Requires-Dist: pyalex>=0.14
Requires-Dist: tqdm>=4.65.0
Requires-Dist: requests
Requires-Dist: pyarrow
Dynamic: license-file
